Metadata-Version: 2.1
Name: xyzt
Version: 0.0.1
Summary: Compute and plot timing scalings for functions with numpy array inputs
Home-page: https://github.com/nosarthur/xyzt
Author: Dong Zhou
Author-email: zhou.dong@gmail.com
License: MIT
Keywords: bash
Platform: linux
Platform: osx
Platform: win32
Classifier: Development Status :: 4 - Beta
Classifier: Intended Audience :: Developers
Classifier: License :: OSI Approved :: MIT License
Classifier: Operating System :: POSIX
Classifier: Operating System :: MacOS :: MacOS X
Classifier: Topic :: Utilities
Classifier: Programming Language :: Python :: 3.6
Classifier: Programming Language :: Python :: 3.7
Classifier: Programming Language :: Python :: 3.8
Classifier: Programming Language :: Python :: 3.9
Requires-Python: ~=3.6
License-File: LICENSE
